Verilog/Test/full_adder.v
`timescale 1ns/1ps
module full_adder(
input a,b,cin,
output wire sum,cout);
assign sum = a^b^cin;
assign cout = (a&b)|(a&cin)|(cin&b);
endmodule

Verilog/Test/full_adder_tb.v
`timescale 1ns/1ps
module full_adder_tb;
reg a,b,cin;
wire sum,cout;
full_adder FA1(a,b,cin,sum,cout);
integer i;
initial begin
$dumpfile("full_adder_tb.vcd");
$dumpvars(0,full_adder_tb);
end
initial begin
for(i=0;i<=7;i=i+1) begin
	{a,b,cin} = i;
	#1;
	$display(" Time = %0t a = %0b b = %0b cin = %0b cout = %0b sum = %0b",$time,a,b,cin,cout,sum);

	end
#10;
$finish;
end
endmodule

Verilog/Test/full_adder_tb.vcd
$date
	Thu Aug 21 09:43:48 2025
$end
$version
	Icarus Verilog
$end
$timescale
	1ps
$end
$scope module full_adder_tb $end
$var wire 1 ! sum $end
$var wire 1 " cout $end
$var reg 1 # a $end
$var reg 1 $ b $end
$var reg 1 % cin $end
$var integer 32 & i [31:0] $end
$scope module FA1 $end
$var wire 1 # a $end
$var wire 1 $ b $end
$var wire 1 % cin $end
$var wire 1 " cout $end
$var wire 1 ! sum $end
$upscope $end
$upscope $end
$enddefinitions $end
$comment Show the parameter values. $end
$dumpall
$end
#0
$dumpvars
b0 &
0%
0$
0#
0"
0!
$end
#1000
1!
1%
b1 &
#2000
1!
1$
0%
b10 &
#3000
1"
0!
1%
b11 &
#4000
0"
1!
1#
0$
0%
b100 &
#5000
1"
0!
1%
b101 &
#6000
0!
1$
0%
b110 &
#7000
1!
1%
b111 &
#8000
b1000 &
